deep_daze/__init__.py
deep_daze/cli.py
deep_daze/clip.py
deep_daze/deep_daze.py
deep_daze/version.py
deep_daze/data/bpe_simple_vocab_16e6.txt
deep_daze-0.11.1.dist-info/LICENSE
deep_daze-0.11.1.dist-info/METADATA
deep_daze-0.11.1.dist-info/WHEEL
deep_daze-0.11.1.dist-info/entry_points.txt
deep_daze-0.11.1.dist-info/top_level.txt
deep_daze-0.11.1.dist-info/RECORD
